2101MC31_Lab10/Assignments/Task_2_full_adder.v
module full_adder(a,b,c,sum,carry);
  input a,b,c;
  output sum,carry;
  wire sum1,carry1,carry2;
 
  half_adder h1(.a(a),.b(b),.s(sum1),.c(carry1));
  half_adder h2(.a(sum1),.b(c),.s(sum),.c(carry2));
  or o1(carry,carry1,carry2);
endmodule : full_adder

           
module half_adder(a,b,s,c); 
  input a,b;
  output s,c;
  
  xor x1(s,a,b);
  and a1(c,a,b);
endmodule :half_adder

2101MC31_Lab10/Assignments/tb_task_2_full_adder.v
module tb_full_adder;
reg a,b,c;
wire sum,carry;
 
  
  full_adder f1(.a(a),.b(b),.c(c),.sum(sum),.carry(carry));
 
  initial begin $dumpfile("tb_full_adder.vcd");$dumpvars(); end

// insert all the inputs 
  initial begin a=1'b1;  #4; a=1'b0;#10 $stop();end
  initial begin b=1'b1; forever #2 b=~b;end
  initial begin c=1'b1;forever #1 c=~c; #10 $stop();end

// monitor all the input and output ports at times 
// when any of the input changes its state

 initial begin $monitor("time=%0d A=%b B=%b 
                          C=%b Sum=%b Carry=%b",$time,a,b,c,sum,carry); end

 endmodule

2101MC31_Lab10/Assignments/tb_full_adder.vcd
$date
	Wed Nov 02 11:53:51 2022
$end
$version
	ModelSim Version 2020.1
$end
$timescale
	1ps
$end

$scope module tb_full_adder $end
$var reg 1 ! a $end
$var reg 1 " b $end
$var reg 1 # c $end
$var wire 1 $ sum $end
$var wire 1 % carry $end

$scope module f1 $end
$var wire 1 & a $end
$var wire 1 ' b $end
$var wire 1 ( c $end
$var wire 1 $ sum $end
$var wire 1 % carry $end
$var wire 1 ) sum1 $end
$var wire 1 * carry1 $end
$var wire 1 + carry2 $end

$scope module h1 $end
$var wire 1 & a $end
$var wire 1 ' b $end
$var wire 1 ) s $end
$var wire 1 * c $end
$upscope $end

$scope module h2 $end
$var wire 1 ) a $end
$var wire 1 ( b $end
$var wire 1 $ s $end
$var wire 1 + c $end
$upscope $end
$upscope $end
$upscope $end
$enddefinitions $end
#0
$dumpvars
1!
1"
1#
1$
1%
0)
1*
0+
1(
1'
1&
$end
#1
0#
0(
0$
#2
0"
1#
0'
1(
0*
1)
1$
0%
1+
0$
1%
#3
0#
0(
0+
1$
0%
#4
0!
1"
1#
0&
1'
1(
1+
0$
1%
#5
0#
0(
0+
1$
0%
#6
0"
1#
0'
1(
0)
1+
0$
0+
1$
1%
0%
#7
0#
0(
0$
#8
1"
1#
1'
1(
1)
1$
1+
0$
1%
#9
0#
0(
0+
1$
0%
#10
0"
1#
0'
1(
0)
1+
0$
0+
1$
1%
0%
#11
0#
0(
0$
#12
1"
1#
1'
1(
1)
1$
1+
0$
1%
#13
0#
0(
0+
1$
0%
